[
  {
    "full_name": "datreeio/datree",
    "stargazers_count": 5922,
    "open_issues_count": 35,
    "forks_count": 282
  },
  {
    "full_name": "dailydotdev/daily",
    "stargazers_count": 8484,
    "open_issues_count": 32,
    "forks_count": 313
  },
  {
    "full_name": "EddieHubCommunity/hacktoberfest-practice",
    "stargazers_count": 316,
    "open_issues_count": 45,
    "forks_count": 1437
  },
  {
    "full_name": "verma-kunal/DevOps-90",
    "stargazers_count": 133,
    "open_issues_count": 2,
    "forks_count": 21
  },
  {
    "full_name": "Dun-sin/Code-Magic",
    "stargazers_count": 86,
    "open_issues_count": 13,
    "forks_count": 57
  },
  {
    "full_name": "30-seconds/30-seconds-of-interviews",
    "stargazers_count": 10653,
    "open_issues_count": 17,
    "forks_count": 944
  },
  {
    "full_name": "sanyam810/LeetCode_TopicWise_Problems",
    "stargazers_count": 1,
    "open_issues_count": 0,
    "forks_count": 0
  },
  {
    "full_name": "kunal-kushwaha/DevOps-Bootcamp",
    "stargazers_count": 1324,
    "open_issues_count": 27,
    "forks_count": 552
  },
  {
    "full_name": "sanyam810/ERC20_Token",
    "stargazers_count": 1,
    "open_issues_count": 0,
    "forks_count": 0
  },
  {
    "full_name": "sanyam810/Crowdfunding_Smart_Contract",
    "stargazers_count": 1,
    "open_issues_count": 0,
    "forks_count": 0
  },
  {
    "full_name": "sanyam810/Auction_Smart_Contract",
    "stargazers_count": 1,
    "open_issues_count": 0,
    "forks_count": 0
  },
  {
    "full_name": "sanyam810/Lottery_Smart_Contract",
    "stargazers_count": 1,
    "open_issues_count": 0,
    "forks_count": 0
  },
  {
    "full_name": "sanyam810/Covid-19_Symptoms_Detection",
    "stargazers_count": 1,
    "open_issues_count": 0,
    "forks_count": 0
  }
]