[
  {
    "full_name": "apteryxxyz/next-ws",
    "stargazers_count": 77,
    "open_issues_count": 5,
    "forks_count": 7
  },
  {
    "full_name": "conductor-oss/conductor",
    "stargazers_count": 6088,
    "open_issues_count": 33,
    "forks_count": 174
  },
  {
    "full_name": "wayoda/LedControl",
    "stargazers_count": 455,
    "open_issues_count": 40,
    "forks_count": 238
  },
  {
    "full_name": "godspeedsystems/gs-node-service",
    "stargazers_count": 595,
    "open_issues_count": 50,
    "forks_count": 12
  },
  {
    "full_name": "sanyam810/The-Bagel-Effect",
    "stargazers_count": 3,
    "open_issues_count": 0,
    "forks_count": 2
  },
  {
    "full_name": "WeMakeDevs/roadmaps",
    "stargazers_count": 3822,
    "open_issues_count": 44,
    "forks_count": 1191
  },
  {
    "full_name": "sanyam810/foodfulLanding",
    "stargazers_count": 3,
    "open_issues_count": 1,
    "forks_count": 1
  },
  {
    "full_name": "adrianhajdin/project_3D_developer_portfolio",
    "stargazers_count": 5031,
    "open_issues_count": 88,
    "forks_count": 1102
  },
  {
    "full_name": "Google-Summer-of-Code-Archive/gsoc-proposals-archive",
    "stargazers_count": 403,
    "open_issues_count": 1,
    "forks_count": 107
  },
  {
    "full_name": "sanyam810/conductor",
    "stargazers_count": 1,
    "open_issues_count": 0,
    "forks_count": 0
  },
  {
    "full_name": "Netflix/conductor",
    "stargazers_count": 12923,
    "open_issues_count": 165,
    "forks_count": 2336
  },
  {
    "full_name": "datreeio/datree",
    "stargazers_count": 6401,
    "open_issues_count": 26,
    "forks_count": 357
  },
  {
    "full_name": "dailydotdev/daily",
    "stargazers_count": 16032,
    "open_issues_count": 19,
    "forks_count": 415
  },
  {
    "full_name": "EddieHubCommunity/open-source-practice",
    "stargazers_count": 612,
    "open_issues_count": 16,
    "forks_count": 2614
  },
  {
    "full_name": "verma-kunal/DevOps-90",
    "stargazers_count": 157,
    "open_issues_count": 2,
    "forks_count": 44
  },
  {
    "full_name": "Dun-sin/Code-Magic",
    "stargazers_count": 370,
    "open_issues_count": 5,
    "forks_count": 197
  },
  {
    "full_name": "Chalarangelo/30-seconds-of-interviews",
    "stargazers_count": 11881,
    "open_issues_count": 20,
    "forks_count": 960
  },
  {
    "full_name": "sanyam810/LeetCode_TopicWise_Problems",
    "stargazers_count": 1,
    "open_issues_count": 0,
    "forks_count": 0
  },
  {
    "full_name": "kunal-kushwaha/DevOps-Bootcamp",
    "stargazers_count": 1972,
    "open_issues_count": 61,
    "forks_count": 1101
  },
  {
    "full_name": "sanyam810/ERC20_Token",
    "stargazers_count": 1,
    "open_issues_count": 0,
    "forks_count": 0
  },
  {
    "full_name": "sanyam810/Crowdfunding_Smart_Contract",
    "stargazers_count": 1,
    "open_issues_count": 0,
    "forks_count": 0
  },
  {
    "full_name": "sanyam810/Auction_Smart_Contract",
    "stargazers_count": 1,
    "open_issues_count": 0,
    "forks_count": 0
  },
  {
    "full_name": "sanyam810/Lottery_Smart_Contract",
    "stargazers_count": 1,
    "open_issues_count": 0,
    "forks_count": 0
  },
  {
    "full_name": "sanyam810/Covid-19_Symptoms_Detection",
    "stargazers_count": 1,
    "open_issues_count": 0,
    "forks_count": 0
  }
]